.travis.yml
README.rst
bootstrap.py
buildout.cfg
setup.cfg
setup.py
test-4.0.x.cfg
test-4.1.x.cfg
test-4.2.x.cfg
test-4.3.x.cfg
collective/__init__.py
collective.portlet.shelf.egg-info/PKG-INFO
collective.portlet.shelf.egg-info/SOURCES.txt
collective.portlet.shelf.egg-info/dependency_links.txt
collective.portlet.shelf.egg-info/entry_points.txt
collective.portlet.shelf.egg-info/namespace_packages.txt
collective.portlet.shelf.egg-info/not-zip-safe
collective.portlet.shelf.egg-info/requires.txt
collective.portlet.shelf.egg-info/top_level.txt
collective/portlet/__init__.py
collective/portlet/shelf/__init__.py
collective/portlet/shelf/configure.zcml
collective/portlet/shelf/portletshelf.pt
collective/portlet/shelf/portletshelf.py
collective/portlet/shelf/browser/__init__.py
collective/portlet/shelf/browser/configure.zcml
collective/portlet/shelf/browser/resources/jquery.tools.min.js
collective/portlet/shelf/browser/resources/shelf.css
collective/portlet/shelf/browser/resources/shelf.js
collective/portlet/shelf/browser/templates/portlet_default_view.pt
collective/portlet/shelf/browser/templates/portlet_image_view.pt
collective/portlet/shelf/browser/templates/portlet_image_view_dx.pt
collective/portlet/shelf/browser/templates/portlet_news_view.pt
collective/portlet/shelf/browser/templates/portlet_news_view_dx.pt
collective/portlet/shelf/locales/collective.portlet.shelf.pot
collective/portlet/shelf/locales/da/LC_MESSAGES/collective.portlet.shelf.po
collective/portlet/shelf/profiles/default/cssregistry.xml
collective/portlet/shelf/profiles/default/jsregistry.xml
collective/portlet/shelf/profiles/default/metadata.xml
collective/portlet/shelf/profiles/default/portlets.xml
collective/portlet/shelf/tests/__init__.py
collective/portlet/shelf/tests/base.py
collective/portlet/shelf/tests/portlet_default_view.pt
collective/portlet/shelf/tests/portlet_image_view.pt
collective/portlet/shelf/tests/test_portlet.py
collective/portlet/shelf/tests/testing.zcml
docs/HISTORY.rst
docs/INSTALL.txt
docs/LICENSE.GPL
docs/LICENSE.txt