Metadata-Version: 1.0
Name: collective.portlet.shelf
Version: 1.3
Summary: collective.portlet.shelf is a portlet for Plone 4 that allows to display Collection's results in a carousel portlet browsing them by subcollections.
Home-page: https://github.com/collective/collective.portlet.shelf
Author: Quintagroup
Author-email: support@quintagroup.com
License: GPL
Keywords: plone portlet shelf
Platform: UNKNOWN
Classifier: Environment :: Web Environment
Classifier: Framework :: Zope2
Classifier: Framework :: Plone
Classifier: Framework :: Plone :: 4.0
Classifier: Framework :: Plone :: 4.1
Classifier: Framework :: Plone :: 4.2
Classifier: Framework :: Plone :: 4.3
Classifier: Programming Language :: Python
Classifier: Development Status :: 4 - Beta
Classifier: Intended Audience :: Developers
Classifier: Natural Language :: English
Classifier: Operating System :: OS Independent
Classifier: Topic :: Internet :: WWW/HTTP :: Dynamic Content
Classifier: Topic :: Software Development :: Libraries :: Python Modules
Classifier: License :: OSI Approved :: GNU General Public License (GPL)
